rfr123/__init__.py
rfr123/download_file.py
rfr123-0.1.dist-info/LICENSE
rfr123-0.1.dist-info/METADATA
rfr123-0.1.dist-info/WHEEL
rfr123-0.1.dist-info/entry_points.txt
rfr123-0.1.dist-info/top_level.txt
rfr123-0.1.dist-info/RECORD
