Metadata-Version: 2.1
Name: rfr123
Version: 0.1
Summary: Download RFR.Java from GitHub
Author: Rajesh
License: MIT
Requires-Python: >=3.6
License-File: LICENSE
